sqly/__init__.py
sqly/__main__.py
sqly/dialect.py
sqly/lib.py
sqly/migration.py
sqly/queries.py
sqly/query.py
sqly/sql.py
sqly/migrations/20211105034808482_init.yaml
testapp/__init__.py
sqly-0.11.0.dist-info/LICENSE
sqly-0.11.0.dist-info/METADATA
sqly-0.11.0.dist-info/WHEEL
sqly-0.11.0.dist-info/entry_points.txt
sqly-0.11.0.dist-info/top_level.txt
sqly-0.11.0.dist-info/RECORD
