Metadata-Version: 2.1
Name: sqly
Version: 0.11.0
Summary: Write SQL in SQL
Home-page: https://github.com/kruxia/sqly
Author: Sean Harrison
Author-email: sah@kruxia.com
License: MPL 2.0
Platform: UNKNOWN
Classifier: Development Status :: 3 - Alpha
Classifier: Intended Audience :: Developers
Classifier: License :: OSI Approved :: Mozilla Public License 2.0 (MPL 2.0)
Classifier: Programming Language :: Python :: 3
License-File: LICENSE
Provides-Extra: dev
Requires-Dist: black (~=23.3.0) ; extra == 'dev'
Requires-Dist: ipython (~=8.12.0) ; extra == 'dev'
Requires-Dist: isort (~=5.12.0) ; extra == 'dev'
Requires-Dist: twine (~=4.0.2) ; extra == 'dev'
Provides-Extra: docs
Requires-Dist: mkdocs-autorefs (~=0.4.1) ; extra == 'docs'
Requires-Dist: mkdocs-click (~=0.8.0) ; extra == 'docs'
Requires-Dist: mkdocs-material-extensions (~=1.1.1) ; extra == 'docs'
Requires-Dist: mkdocs-material (~=9.1.19) ; extra == 'docs'
Requires-Dist: mkdocstrings-python (~=1.2.1) ; extra == 'docs'
Requires-Dist: mkdocstrings (~=0.22.0) ; extra == 'docs'
Requires-Dist: mkdocs (~=1.4.3) ; extra == 'docs'
Requires-Dist: sqly[migration] ; extra == 'docs'
Provides-Extra: migration
Requires-Dist: PyYAML (~=6.0) ; extra == 'migration'
Requires-Dist: click (~=8.1.3) ; extra == 'migration'
Requires-Dist: networkx (~=3.1) ; extra == 'migration'
Provides-Extra: psycopg
Requires-Dist: psycopg[binary] (~=3.1.9) ; extra == 'psycopg'
Provides-Extra: test
Requires-Dist: black (~=23.3.0) ; extra == 'test'
Requires-Dist: flake8 (~=6.0.0) ; extra == 'test'
Requires-Dist: mypy ; extra == 'test'
Requires-Dist: psycopg[binary] (~=3.1.9) ; extra == 'test'
Requires-Dist: pytest-click (~=1.1.0) ; extra == 'test'
Requires-Dist: pytest-cov (~=4.0.0) ; extra == 'test'
Requires-Dist: pytest (~=7.3.1) ; extra == 'test'
Requires-Dist: sqly[migration] ; extra == 'test'
